.gitignore
MANIFEST.in
README.rst
setup.cfg
setup.py
docs/HISTORY.txt
docs/LICENSE.GPL
docs/LICENSE.txt
docs/MANUAL.txt
raptus/__init__.py
raptus.article.links.egg-info/PKG-INFO
raptus.article.links.egg-info/SOURCES.txt
raptus.article.links.egg-info/dependency_links.txt
raptus.article.links.egg-info/entry_points.txt
raptus.article.links.egg-info/namespace_packages.txt
raptus.article.links.egg-info/not-zip-safe
raptus.article.links.egg-info/requires.txt
raptus.article.links.egg-info/top_level.txt
raptus/article/__init__.py
raptus/article/links/__init__.py
raptus/article/links/configure.zcml
raptus/article/links/interfaces.py
raptus/article/links/links.py
raptus/article/links/browser/__init__.py
raptus/article/links/browser/configure.zcml
raptus/article/links/browser/links.gif
raptus/article/links/browser/links.pt
raptus/article/links/browser/links.py
raptus/article/links/i18n/raptus.article-de.mo
raptus/article/links/i18n/raptus.article-de.po
raptus/article/links/i18n/raptus.article-fr.mo
raptus/article/links/i18n/raptus.article-fr.po
raptus/article/links/i18n/raptus.article-it.mo
raptus/article/links/i18n/raptus.article-it.po
raptus/article/links/i18n/raptus.article.pot
raptus/article/links/profiles/default/metadata.xml
raptus/article/links/profiles/default/types.xml
raptus/article/links/profiles/default/viewlets.xml
raptus/article/links/profiles/default/workflows.xml
raptus/article/links/profiles/default/types/Article.xml