Metadata-Version: 1.1
Name: raptus.article.links
Version: 2.0b6
Summary: Provides support for adding links to articles.
Home-page: https://github.com/Raptus/raptus.article.links
Author: Raptus AG
Author-email: dev@raptus.com
License: GPL
Platform: UNKNOWN
Classifier: Programming Language :: Python
Classifier: Topic :: Software Development :: Libraries :: Python Modules
